{
  "pexels-photo-1684880.webp": "both",
  "pexels-photo-2280547.webp": "wedding",
  "pexels-photo-4021773.webp": "engagement",
  "7SUN5334.JPG": "wedding",
  "6N6A0080.JPG": "wedding",
  "7SUN5351.JPG": "wedding",
  "7SUN5352.JPG": "wedding",
  "7SUN5354.JPG": "wedding",
  "7SUN5357.JPG": "wedding",
  "7SUN5361.JPG": "wedding",
  "7SUN5363.JPG": "wedding",
  "7SUN5365.JPG": "wedding",
  "7SUN5366.JPG": "wedding",
  "7SUN5374.JPG": "wedding",
  "7SUN5377.JPG": "wedding",
  "7SUN5380.JPG": "wedding",
  "7SUN5384.JPG": "wedding",
  "7SUN5388.JPG": "wedding",
  "7SUN5393.JPG": "wedding",
  "7SUN5404.JPG": "wedding",
  "7SUN5407.JPG": "wedding",
  "7SUN5410.JPG": "wedding",
  "7SUN5414.JPG": "wedding",
  "7SUN5422.JPG": "wedding",
  "7SUN5431.JPG": "wedding",
  "7SUN5443.JPG": "wedding",
  "7SUN5446.JPG": "wedding",
  "7SUN5450.JPG": "wedding",
  "7SUN5451.JPG": "wedding",
  "7SUN5454.JPG": "wedding",
  "7SUN5456.JPG": "wedding",
  "7SUN5461.JPG": "wedding",
  "7SUN5465.JPG": "wedding",
  "7SUN5466.JPG": "wedding",
  "7SUN5470.JPG": "wedding",
  "7SUN5474.JPG": "wedding",
  "7SUN5475.JPG": "wedding",
  "7SUN5479.JPG": "wedding",
  "7SUN5486.JPG": "wedding",
  "7SUN5488.JPG": "wedding",
  "7SUN5489.JPG": "wedding",
  "7SUN5496.JPG": "wedding",
  "7SUN5497.JPG": "wedding",
  "7SUN5502.JPG": "wedding",
  "7SUN5504.JPG": "wedding",
  "7SUN5505.JPG": "wedding",
  "7SUN5507.JPG": "wedding",
  "7SUN5509.JPG": "wedding",
  "7SUN5510.JPG": "wedding",
  "7SUN5512.JPG": "wedding",
  "7SUN5514.JPG": "wedding",
  "7SUN5517.JPG": "wedding",
  "7SUN5528.JPG": "wedding",
  "7SUN5530.JPG": "wedding",
  "7SUN5533.JPG": "wedding",
  "7SUN5534.JPG": "wedding",
  "7SUN5539.JPG": "wedding",
  "7SUN5555.JPG": "wedding",
  "7SUN5561.JPG": "wedding",
  "7SUN5563.JPG": "wedding",
  "7SUN5564.JPG": "wedding",
  "7SUN5579.JPG": "wedding",
  "7SUN5588.JPG": "wedding",
  "7SUN5601.JPG": "wedding",
  "7SUN5609.JPG": "wedding",
  "7SUN5613.JPG": "wedding",
  "7SUN5631.JPG": "wedding",
  "7SUN5632.JPG": "wedding",
  "7SUN5634.JPG": "wedding",
  "7SUN5649.JPG": "wedding",
  "7SUN5650.JPG": "wedding",
  "7SUN5659.JPG": "wedding",
  "7SUN5660.JPG": "wedding",
  "7SUN5663.JPG": "wedding",
  "7SUN5668.JPG": "wedding",
  "7SUN5674.JPG": "wedding",
  "7SUN5690.JPG": "wedding",
  "7SUN5709.JPG": "wedding",
  "7SUN5710.JPG": "wedding",
  "7SUN5714.JPG": "wedding",
  "7SUN5728.JPG": "wedding",
  "7SUN5730.JPG": "wedding",
  "7SUN5731.JPG": "wedding",
  "7SUN5734.JPG": "wedding",
  "7SUN5740.JPG": "wedding",
  "7SUN5751.JPG": "wedding",
  "7SUN5760.JPG": "wedding",
  "7SUN5765.JPG": "wedding",
  "7SUN5782.JPG": "wedding",
  "7SUN5792.JPG": "wedding",
  "7SUN5794.JPG": "wedding",
  "7SUN5795.JPG": "wedding",
  "7SUN5802.JPG": "wedding",
  "7SUN5822.JPG": "wedding",
  "7SUN5846.JPG": "wedding",
  "7SUN5847.JPG": "wedding",
  "7SUN5849.JPG": "wedding",
  "7SUN5851.JPG": "wedding",
  "7SUN5853.JPG": "wedding",
  "7SUN5859.JPG": "wedding",
  "7SUN5860.JPG": "wedding",
  "7SUN5861.JPG": "wedding",
  "7SUN5866.JPG": "wedding",
  "7SUN5869.JPG": "wedding",
  "7SUN5882.JPG": "wedding",
  "7SUN5890.JPG": "wedding",
  "7SUN5888.JPG": "wedding",
  "7SUN5896.JPG": "wedding",
  "7SUN5895.JPG": "wedding",
  "7SUN5897.JPG": "wedding",
  "7SUN5901.JPG": "wedding",
  "7SUN5905.JPG": "wedding",
  "7SUN5910.JPG": "wedding",
  "7SUN5911.JPG": "wedding",
  "7SUN5912.JPG": "wedding",
  "7SUN5913.JPG": "wedding",
  "7SUN5916.JPG": "wedding",
  "7SUN5917.JPG": "wedding",
  "7SUN5918.JPG": "wedding",
  "7SUN5919.JPG": "wedding",
  "7SUN5922.JPG": "wedding",
  "7SUN5924.JPG": "wedding",
  "7SUN5925.JPG": "wedding",
  "7SUN5930.JPG": "wedding",
  "7SUN5931.JPG": "wedding",
  "7SUN5933.JPG": "wedding",
  "7SUN5934.JPG": "wedding",
  "7SUN5935.JPG": "wedding",
  "7SUN5937.JPG": "wedding",
  "7SUN5939.JPG": "wedding",
  "7SUN5940.JPG": "wedding",
  "7SUN5944.JPG": "wedding",
  "7SUN5948.JPG": "wedding",
  "7SUN5951.JPG": "wedding",
  "7SUN5952.JPG": "wedding",
  "7SUN5955.JPG": "wedding",
  "7SUN5956.JPG": "wedding",
  "7SUN5957.JPG": "wedding",
  "7SUN5959.JPG": "wedding",
  "7SUN5966.JPG": "wedding",
  "7SUN5967.JPG": "wedding",
  "7SUN5969.JPG": "wedding",
  "7SUN5971.JPG": "wedding",
  "7SUN5973.JPG": "wedding",
  "7SUN5974.JPG": "wedding",
  "7SUN5975.JPG": "wedding",
  "7SUN5977.JPG": "wedding",
  "7SUN5979.JPG": "wedding",
  "7SUN5980.JPG": "wedding",
  "7SUN5982.JPG": "wedding",
  "7SUN5983.JPG": "wedding",
  "7SUN5984.JPG": "wedding",
  "7SUN5985.JPG": "wedding",
  "7SUN5986.JPG": "wedding",
  "7SUN5987.JPG": "wedding",
  "7SUN5988.JPG": "wedding",
  "7SUN5989.JPG": "wedding",
  "7SUN5992.JPG": "wedding",
  "7SUN5993.JPG": "wedding",
  "7SUN5994.JPG": "wedding",
  "7SUN5995.JPG": "wedding",
  "7SUN5997.JPG": "wedding",
  "7SUN6004.JPG": "wedding",
  "7SUN6005.JPG": "wedding",
  "7SUN6008.JPG": "wedding",
  "7SUN6009.JPG": "wedding",
  "7SUN6010.JPG": "wedding",
  "7SUN6012.JPG": "wedding",
  "7SUN6016.JPG": "wedding",
  "7SUN6019.JPG": "wedding",
  "7SUN6030.JPG": "wedding"
}